mongodb_connect/__init__.py
mongodb_connect/mongo_crud.py
dbconnector_auto-0.0.0.dist-info/METADATA
dbconnector_auto-0.0.0.dist-info/WHEEL
dbconnector_auto-0.0.0.dist-info/top_level.txt
dbconnector_auto-0.0.0.dist-info/RECORD
